managecor/__init__.py
managecor/cli.py
managecor/docker_utils.py
managecor/jupytercor.py
managecor/pdfcor.py
managecor-0.3.5.dist-info/LICENSE
managecor-0.3.5.dist-info/METADATA
managecor-0.3.5.dist-info/WHEEL
managecor-0.3.5.dist-info/entry_points.txt
managecor-0.3.5.dist-info/RECORD
