Metadata-Version: 2.1
Name: managecor
Version: 0.3.5
Summary: 
Author: infocornouaille
Author-email: 90894019+infocornouaille@users.noreply.github.com
Requires-Python: >=3.11,<4.0
Classifier: Programming Language :: Python :: 3
Classifier: Programming Language :: Python :: 3.11
Classifier: Programming Language :: Python :: 3.12
Requires-Dist: docker (>=7.1.0,<8.0.0)
Requires-Dist: pyyaml (>=6.0.2,<7.0.0)
Requires-Dist: requests (>=2.32.3,<3.0.0)
Requires-Dist: rich (>=13.9.3,<14.0.0)
Requires-Dist: typer (>=0.12.5,<0.13.0)
